[
  {
    "Keyword": "add",
    "Description": "Adds new shortcut.",
    "Example": "add [keyword] [path]"
  },
  {
    "Keyword": "var",
    "Description": "Shows or sets variable.",
    "Example": "var [name] [value]"
  },
  {
    "Keyword": "remove",
    "Description": "Removes shortcut.",
    "Example": "remove [keyword]"
  },
  {
    "Keyword": "path",
    "Description": "Shows shortcut path.",
    "Example": "path [keyword]"
  },
  {
    "Keyword": "keyword",
    "Description": "Shows or sets plugin keyword.",
    "Example": "keyword [newKeyword]"
  },
  {
    "Keyword": "duplicate",
    "Description": "Duplicates shortcut.",
    "Example": "duplicate [source] [destination]"
  },
  {
    "Keyword": "settings",
    "Description": "Opens Flow Launcher settings.",
    "Example": "settings"
  },
  {
    "Keyword": "config",
    "Description": "Opens config file.",
    "Example": "config"
  },
  {
    "Keyword": "helpers",
    "Description": "Opens helpers file.",
    "Example": "helpers"
  },
  {
    "Keyword": "reload",
    "Description": "Reloads plugin.",
    "Example": "reload"
  },
  {
    "Keyword": "help",
    "Description": "Shows this help.",
    "Example": "help"
  },
  {
    "Keyword": "list",
    "Description": "Shows list of shortcuts.",
    "Example": "list"
  },
  {
    "Keyword": "import",
    "Description": "Imports shortcuts from JSON file.",
    "Example": "import"
  },
  {
    "Keyword": "export",
    "Description": "Exports shortcuts to JSON file.",
    "Example": "export"
  }
]